{"address_components": [{"long_name": "63", "short_name": "63", "types": ["street_number"]}, {"long_name": "Boulevard Berthelot", "short_name": "Bd Berthelot", "types": ["route"]}, {"long_name": "Clermont-Ferrand", "short_name": "Clermont-Ferrand", "types": ["locality", "political"]}, {"long_name": "Puy-de-D\u00f4me", "short_name": "Puy-de-D\u00f4me", "types": ["administrative_area_level_2", "political"]}, {"long_name": "Auvergne-Rh\u00f4ne-Alpes", "short_name": "Auvergne-Rh\u00f4ne-Alpes", "types": ["administrative_area_level_1", "political"]}, {"long_name": "France", "short_name": "FR", "types": ["country", "political"]}, {"long_name": "63000", "short_name": "63000", "types": ["postal_code"]}], "adr_address": "<span class=\"street-address\">63 Bd Berthelot</span>, <span class=\"postal-code\">63000</span> <span class=\"locality\">Clermont-Ferrand</span>, <span class=\"country-name\">France</span>", "business_status": "OPERATIONAL", "formatted_address": "63 Bd Berthelot, 63000 Clermont-Ferrand, France", "geometry": {"location": {"lat": 45.7819134, "lng": 3.0712445}, "viewport": {"northeast": {"lat": 45.7832535302915, "lng": 3.072771630291502}, "southwest": {"lat": 45.7805555697085, "lng": 3.070073669708498}}}, "icon": "https://maps.gstatic.com/mapfiles/place_api/icons/v1/png_71/lodging-71.png", "icon_background_color": "#909CE1", "icon_mask_base_uri": "https://maps.gstatic.com/mapfiles/place_api/icons/v2/hotel_pinlet", "name": "Clermont-Ferrand", "place_id": "ChIJab4jbACvthIRzAL7XMmE5TY", "plus_code": {"compound_code": "Q3JC+QF Clermont-Ferrand, France", "global_code": "8FQ5Q3JC+QF"}, "rating": 4, "reference": "ChIJab4jbACvthIRzAL7XMmE5TY", "reviews": [{"author_name": "Cesare Pescatore", "author_url": "https://www.google.com/maps/contrib/102072841763459248342/reviews", "profile_photo_url": "https://lh3.googleusercontent.com/a/ACg8ocKzj4KPS8zGRjSRc5Y3iyn8npZ5kUDlhaSPYjNVAvb2b7ZC7g=s128-c0x00000000-cc-rp-mo", "rating": 4, "relative_time_description": "a year ago", "text": "", "time": 1717771390, "translated": false}], "types": ["establishment", "lodging", "point_of_interest"], "url": "https://maps.google.com/?cid=3955713848098095820", "user_ratings_total": 1, "utc_offset": 120, "vicinity": "63 Bd Berthelot, Clermont-Ferrand"}